MANIFEST.in
setup.cfg
setup.py
js/__init__.py
js.fuelux.egg-info/PKG-INFO
js.fuelux.egg-info/SOURCES.txt
js.fuelux.egg-info/dependency_links.txt
js.fuelux.egg-info/entry_points.txt
js.fuelux.egg-info/namespace_packages.txt
js.fuelux.egg-info/not-zip-safe
js.fuelux.egg-info/requires.txt
js.fuelux.egg-info/top_level.txt
js/fuelux/__init__.py
js/fuelux/resources/css/fuelux-responsive.css
js/fuelux/resources/css/fuelux-responsive.min.css
js/fuelux/resources/css/fuelux.css
js/fuelux/resources/css/fuelux.min.css
js/fuelux/resources/js/all.js
js/fuelux/resources/js/all.min.js
js/fuelux/resources/js/checkbox.js
js/fuelux/resources/js/combobox.js
js/fuelux/resources/js/datagrid.js
js/fuelux/resources/js/datepicker.js
js/fuelux/resources/js/intelligent-dropdown.js
js/fuelux/resources/js/loader.js
js/fuelux/resources/js/loader.min.js
js/fuelux/resources/js/pillbox.js
js/fuelux/resources/js/radio.js
js/fuelux/resources/js/scheduler.js
js/fuelux/resources/js/search.js
js/fuelux/resources/js/select.js
js/fuelux/resources/js/spinner.js
js/fuelux/resources/js/tree.js
js/fuelux/resources/js/util.js
js/fuelux/resources/js/wizard.js