Metadata-Version: 1.0
Name: js.fuelux
Version: 2.5.0
Summary: Fanstatic packaging for FuelUX
Home-page: https://github.com/demsullivan/js.fuelux
Author: Dave Sullivan
Author-email: dave@dave-sullivan.com
License: BSD
Keywords: fanstatic fuelux bootstrap twitter
Platform: UNKNOWN
